README.rst
setup.py
src/pyrpm/__init__.py
src/pyrpm/rpm.py
src/pyrpm/yum.py
src/pyrpm/tools/__init__.py
src/pyrpm/tools/createrepo.py
src/pyrpm_02strich.egg-info/PKG-INFO
src/pyrpm_02strich.egg-info/SOURCES.txt
src/pyrpm_02strich.egg-info/dependency_links.txt
src/pyrpm_02strich.egg-info/requires.txt
src/pyrpm_02strich.egg-info/top_level.txt